scrapy_mcp_server/__init__.py
scrapy_mcp_server/server.py
scrapy_mcp_server/pyarmor_runtime_000000/__init__.py
scrapy_mcp_server/pyarmor_runtime_000000/darwin_aarch64/pyarmor_runtime.so
scrapy_mcp_server/pyarmor_runtime_000000/darwin_x86_64/pyarmor_runtime.so
scrapy_mcp_server/pyarmor_runtime_000000/linux_x86_64/pyarmor_runtime.so
scrapy_mcp_server/pyarmor_runtime_000000/windows_x86_64/pyarmor_runtime.pyd
scrapy_mcp_server-0.1.1.dist-info/licenses/LICENSE
scrapy_mcp_server-0.1.1.dist-info/METADATA
scrapy_mcp_server-0.1.1.dist-info/WHEEL
scrapy_mcp_server-0.1.1.dist-info/entry_points.txt
scrapy_mcp_server-0.1.1.dist-info/top_level.txt
scrapy_mcp_server-0.1.1.dist-info/RECORD
