Metadata-Version: 2.4
Name: scrapy-mcp-server
Version: 0.1.1
Summary: MCP server for Scrapy request inspection and debugging
Author: Fabien Vauchelles
Project-URL: Homepage, https://github.com/scrapoxy/scrapy-mcp-server
Keywords: scrapy,mcp,server,debugging,inspection,parsel,obfuscated
Classifier: Development Status :: 4 - Beta
Classifier: Intended Audience :: Developers
Classifier: Programming Language :: Python :: 3
Classifier: Programming Language :: Python :: 3.8
Classifier: Programming Language :: Python :: 3.9
Classifier: Programming Language :: Python :: 3.10
Classifier: Programming Language :: Python :: 3.11
Classifier: Programming Language :: Python :: 3.12
Classifier: Programming Language :: Python :: 3.13
Classifier: License :: Other/Proprietary License
Classifier: Operating System :: OS Independent
Classifier: Framework :: Scrapy
Requires-Python: >=3.8
License-File: LICENSE
Requires-Dist: fastmcp>=0.1.0
Requires-Dist: scrapy>=2.0.0
Requires-Dist: requests>=2.25.0
Requires-Dist: uvicorn>=0.20.0
Requires-Dist: starlette>=0.20.0
Provides-Extra: dev
Requires-Dist: pyarmor>=9.0; extra == "dev"
Requires-Dist: pytest>=7.0; extra == "dev"
Dynamic: license-file
